[{"__symbolic":"module","version":3,"metadata":{"HorizontalSplitPaneComponent":{"__symbolic":"class","extends":{"__symbolic":"reference","module":"./split-pane.component","name":"SplitPaneComponent"},"decorators":[{"__symbolic":"call","expression":{"__symbolic":"reference","module":"@angular/core","name":"Component"},"arguments":[{"selector":"horizontal-split-pane","styles":["\n    .h-outer {\n      height: 100%;\n      width: 100%;\n      display: flex;\n      flex-flow: column;\n    }\n\n    .upper-component {\n      height: calc(50% - 4px);\n    }\n\n    .lower-component {\n      height: calc(50% - 4px);\n    }\n  "],"template":"\n  <div #outer class=\"h-outer\">\n    <div\n      #primaryComponent\n      [hidden]=\"primaryToggledOff\"\n      class=\"upper-component\">\n      <ng-content select=\".split-pane-content-primary\"></ng-content>\n    </div>\n    <horizontal-split-separator\n      #separator\n      [hidden]=\"primaryToggledOff || secondaryToggledOff\"\n      [thickness]=\"separatorThickness\"\n      (notifyWillChangeSize)=\"notifyWillChangeSize($event)\">\n    </horizontal-split-separator>\n    <div\n      #secondaryComponent\n      [hidden]=\"secondaryToggledOff\"\n      class=\"lower-component\">\n      <ng-content select=\".split-pane-content-secondary\"></ng-content>\n    </div>\n  </div>\n  "}]}],"members":{"outerContainer":[{"__symbolic":"property","decorators":[{"__symbolic":"call","expression":{"__symbolic":"reference","module":"@angular/core","name":"ViewChild"},"arguments":["outer"]}]}],"test":[{"__symbolic":"property","decorators":[{"__symbolic":"call","expression":{"__symbolic":"reference","module":"@angular/core","name":"Input"}}]}],"getTotalSize":[{"__symbolic":"method"}],"getPrimarySize":[{"__symbolic":"method"}],"getSecondarySize":[{"__symbolic":"method"}],"dividerPosition":[{"__symbolic":"method"}],"onMousemove":[{"__symbolic":"method","decorators":[{"__symbolic":"call","expression":{"__symbolic":"reference","module":"@angular/core","name":"HostListener"},"arguments":["mousemove",["$event"]]}]}],"onTouchmove":[{"__symbolic":"method","decorators":[{"__symbolic":"call","expression":{"__symbolic":"reference","module":"@angular/core","name":"HostListener"},"arguments":["touchmove",["$event"]]}]}]}}}},{"__symbolic":"module","version":1,"metadata":{"HorizontalSplitPaneComponent":{"__symbolic":"class","extends":{"__symbolic":"reference","module":"./split-pane.component","name":"SplitPaneComponent"},"decorators":[{"__symbolic":"call","expression":{"__symbolic":"reference","module":"@angular/core","name":"Component"},"arguments":[{"selector":"horizontal-split-pane","styles":["\n    .h-outer {\n      height: 100%;\n      width: 100%;\n      display: flex;\n      flex-flow: column;\n    }\n\n    .upper-component {\n      height: calc(50% - 4px);\n    }\n\n    .lower-component {\n      height: calc(50% - 4px);\n    }\n  "],"template":"\n  <div #outer class=\"h-outer\">\n    <div\n      #primaryComponent\n      [hidden]=\"primaryToggledOff\"\n      class=\"upper-component\">\n      <ng-content select=\".split-pane-content-primary\"></ng-content>\n    </div>\n    <horizontal-split-separator\n      #separator\n      [hidden]=\"primaryToggledOff || secondaryToggledOff\"\n      [thickness]=\"separatorThickness\"\n      (notifyWillChangeSize)=\"notifyWillChangeSize($event)\">\n    </horizontal-split-separator>\n    <div\n      #secondaryComponent\n      [hidden]=\"secondaryToggledOff\"\n      class=\"lower-component\">\n      <ng-content select=\".split-pane-content-secondary\"></ng-content>\n    </div>\n  </div>\n  "}]}],"members":{"outerContainer":[{"__symbolic":"property","decorators":[{"__symbolic":"call","expression":{"__symbolic":"reference","module":"@angular/core","name":"ViewChild"},"arguments":["outer"]}]}],"test":[{"__symbolic":"property","decorators":[{"__symbolic":"call","expression":{"__symbolic":"reference","module":"@angular/core","name":"Input"}}]}],"getTotalSize":[{"__symbolic":"method"}],"getPrimarySize":[{"__symbolic":"method"}],"getSecondarySize":[{"__symbolic":"method"}],"dividerPosition":[{"__symbolic":"method"}],"onMousemove":[{"__symbolic":"method","decorators":[{"__symbolic":"call","expression":{"__symbolic":"reference","module":"@angular/core","name":"HostListener"},"arguments":["mousemove",["$event"]]}]}],"onTouchmove":[{"__symbolic":"method","decorators":[{"__symbolic":"call","expression":{"__symbolic":"reference","module":"@angular/core","name":"HostListener"},"arguments":["touchmove",["$event"]]}]}]}}}}]